[
  {
    "STONE": "0.00023333",
    "FOOD": "0.00022541",
    "SKIN": "0.14900000",
    "WOOD": "0.00020492",
    "date_create": "2024-09-13 00:48:07"
  },
  {
    "FOOD": "0.00022541",
    "STONE": "0.00023333",
    "SKIN": "0.14900000",
    "WOOD": "0.00020491",
    "date_create": "2024-09-13 02:03:52"
  },
  {
    "SKIN": "0.14900000",
    "STONE": "0.00023333",
    "WOOD": "0.00020491",
    "FOOD": "0.00022541",
    "date_create": "2024-09-13 02:48:37"
  },
  {
    "SKIN": "0.14900000",
    "FOOD": "0.00022541",
    "WOOD": "0.00020491",
    "STONE": "0.00023333",
    "date_create": "2024-09-13 03:00:22"
  },
  {
    "SKIN": "0.14900000",
    "STONE": "0.00023333",
    "FOOD": "0.00022541",
    "WOOD": "0.00020491",
    "date_create": "2024-09-13 03:19:32"
  },
  {
    "STONE": "0.00023333",
    "SKIN": "0.14900000",
    "FOOD": "0.00022541",
    "WOOD": "0.00020491",
    "date_create": "2024-09-13 03:32:17"
  },
  {
    "FOOD": "0.00022541",
    "SKIN": "0.14900000",
    "STONE": "0.00023333",
    "WOOD": "0.00020491",
    "date_create": "2024-09-13 03:41:07"
  },
  {
    "SKIN": "0.14900000",
    "FOOD": "0.00022541",
    "STONE": "0.00023333",
    "WOOD": "0.00020491",
    "date_create": "2024-09-13 03:47:17"
  },
  {
    "FOOD": "0.00022541",
    "SKIN": "0.14900000",
    "STONE": "0.00023333",
    "WOOD": "0.00020491",
    "date_create": "2024-09-13 03:53:17"
  },
  {
    "SKIN": "0.14900000",
    "STONE": "0.00023333",
    "WOOD": "0.00020491",
    "FOOD": "0.00022541",
    "date_create": "2024-09-13 03:59:17"
  },
  {
    "FOOD": "0.00022541",
    "SKIN": "0.14900000",
    "STONE": "0.00023333",
    "WOOD": "0.00020491",
    "date_create": "2024-09-13 04:18:07"
  },
  {
    "WOOD": "0.00020491",
    "SKIN": "0.14900000",
    "STONE": "0.00023333",
    "FOOD": "0.00022541",
    "date_create": "2024-09-13 04:33:23"
  },
  {
    "SKIN": "0.14900000",
    "STONE": "0.00023333",
    "WOOD": "0.00020491",
    "FOOD": "0.00022541",
    "date_create": "2024-09-13 04:43:02"
  },
  {
    "SKIN": "0.14900000",
    "STONE": "0.00023333",
    "FOOD": "0.00022541",
    "WOOD": "0.00020491",
    "date_create": "2024-09-13 04:49:02"
  },
  {
    "FOOD": "0.00022541",
    "STONE": "0.00023333",
    "WOOD": "0.00020491",
    "SKIN": "0.14900000",
    "date_create": "2024-09-13 04:55:02"
  },
  {
    "WOOD": "0.00020491",
    "STONE": "0.00023333",
    "SKIN": "0.14900000",
    "FOOD": "0.00022541",
    "date_create": "2024-09-13 05:07:48"
  },
  {
    "WOOD": "0.00020491",
    "FOOD": "0.00022541",
    "SKIN": "0.14444444",
    "STONE": "0.00023333",
    "date_create": "2024-09-13 05:26:33"
  },
  {
    "FOOD": "0.00022541",
    "SKIN": "0.14444444",
    "STONE": "0.00023333",
    "WOOD": "0.00020491",
    "date_create": "2024-09-13 05:36:22"
  },
  {
    "SKIN": "0.14444444",
    "FOOD": "0.00022541",
    "WOOD": "0.00020491",
    "STONE": "0.00023333",
    "date_create": "2024-09-13 05:42:17"
  },
  {
    "SKIN": "0.14444444",
    "WOOD": "0.00020491",
    "STONE": "0.00023333",
    "FOOD": "0.00022541",
    "date_create": "2024-09-13 05:48:02"
  },
  {
    "STONE": "0.00023333",
    "SKIN": "0.14444444",
    "FOOD": "0.00022541",
    "WOOD": "0.00020491",
    "date_create": "2024-09-13 05:54:01"
  },
  {
    "STONE": "0.00023333",
    "FOOD": "0.00022541",
    "WOOD": "0.00020491",
    "SKIN": "0.14444444",
    "date_create": "2024-09-13 05:59:58"
  },
  {
    "STONE": "0.00023333",
    "FOOD": "0.00022541",
    "WOOD": "0.00020491",
    "SKIN": "0.14444444",
    "date_create": "2024-09-13 06:24:28"
  },
  {
    "WOOD": "0.00020491",
    "SKIN": "0.14444444",
    "STONE": "0.00023333",
    "FOOD": "0.00022541",
    "date_create": "2024-09-13 06:40:37"
  },
  {
    "STONE": "0.00023333",
    "FOOD": "0.00022541",
    "SKIN": "0.14444444",
    "WOOD": "0.00020491",
    "date_create": "2024-09-13 06:48:42"
  },
  {
    "STONE": "0.00023333",
    "WOOD": "0.00020491",
    "SKIN": "0.14444444",
    "FOOD": "0.00022541",
    "date_create": "2024-09-13 06:54:38"
  },
  {
    "SKIN": "0.14444444",
    "WOOD": "0.00020491",
    "FOOD": "0.00022541",
    "STONE": "0.00023333",
    "date_create": "2024-09-13 07:06:41"
  },
  {
    "STONE": "0.00023333",
    "WOOD": "0.00020491",
    "SKIN": "0.14444444",
    "FOOD": "0.00022541",
    "date_create": "2024-09-13 07:23:17"
  },
  {
    "FOOD": "0.00022541",
    "SKIN": "0.14444444",
    "STONE": "0.00023333",
    "WOOD": "0.00020491",
    "date_create": "2024-09-13 07:29:32"
  },
  {
    "WOOD": "0.00020491",
    "SKIN": "0.14444444",
    "FOOD": "0.00022541",
    "STONE": "0.00023333",
    "date_create": "2024-09-13 07:35:53"
  },
  {
    "WOOD": "0.00020491",
    "SKIN": "0.14444444",
    "STONE": "0.00023333",
    "FOOD": "0.00022541",
    "date_create": "2024-09-13 07:41:43"
  },
  {
    "WOOD": "0.00020491",
    "SKIN": "0.14444444",
    "STONE": "0.00023333",
    "FOOD": "0.00022541",
    "date_create": "2024-09-13 07:47:53"
  },
  {
    "SKIN": "0.14444444",
    "WOOD": "0.00020491",
    "STONE": "0.00023333",
    "FOOD": "0.00022541",
    "date_create": "2024-09-13 07:53:48"
  },
  {
    "SKIN": "0.14444444",
    "FOOD": "0.00022541",
    "WOOD": "0.00020491",
    "STONE": "0.00023333",
    "date_create": "2024-09-13 07:59:37"
  },
  {
    "WOOD": "0.00020491",
    "STONE": "0.00023333",
    "FOOD": "0.00022541",
    "SKIN": "0.14444444",
    "date_create": "2024-09-13 08:20:18"
  },
  {
    "FOOD": "0.00022541",
    "SKIN": "0.14000000",
    "WOOD": "0.00020491",
    "STONE": "0.00023333",
    "date_create": "2024-09-13 08:35:21"
  },
  {
    "FOOD": "0.00022541",
    "SKIN": "0.14000000",
    "STONE": "0.00023333",
    "WOOD": "0.00020491",
    "date_create": "2024-09-13 08:44:43"
  },
  {
    "FOOD": "0.00022541",
    "STONE": "0.00023333",
    "WOOD": "0.00020491",
    "SKIN": "0.14000000",
    "date_create": "2024-09-13 08:50:43"
  },
  {
    "SKIN": "0.14000000",
    "WOOD": "0.00020491",
    "FOOD": "0.00022541",
    "STONE": "0.00023333",
    "date_create": "2024-09-13 08:56:43"
  },
  {
    "FOOD": "0.00022541",
    "SKIN": "0.14000000",
    "STONE": "0.00023333",
    "WOOD": "0.00020491",
    "date_create": "2024-09-13 09:11:12"
  },
  {
    "STONE": "0.00023333",
    "SKIN": "0.14000000",
    "FOOD": "0.00022541",
    "WOOD": "0.00020491",
    "date_create": "2024-09-13 09:26:42"
  },
  {
    "FOOD": "0.00022541",
    "SKIN": "0.14000000",
    "WOOD": "0.00020491",
    "STONE": "0.00023333",
    "date_create": "2024-09-13 09:34:53"
  },
  {
    "FOOD": "0.00022541",
    "STONE": "0.00023333",
    "WOOD": "0.00020491",
    "SKIN": "0.14000000",
    "date_create": "2024-09-13 09:40:53"
  },
  {
    "SKIN": "0.14000000",
    "WOOD": "0.00020491",
    "STONE": "0.00023333",
    "FOOD": "0.00022541",
    "date_create": "2024-09-13 09:46:47"
  },
  {
    "STONE": "0.00023333",
    "FOOD": "0.00022541",
    "SKIN": "0.14000000",
    "WOOD": "0.00020491",
    "date_create": "2024-09-13 09:52:37"
  },
  {
    "FOOD": "0.00022541",
    "SKIN": "0.14000000",
    "STONE": "0.00023333",
    "WOOD": "0.00020491",
    "date_create": "2024-09-13 09:58:27"
  },
  {
    "SKIN": "0.13500000",
    "FOOD": "0.00022541",
    "STONE": "0.00023333",
    "WOOD": "0.00020491",
    "date_create": "2024-09-13 10:14:42"
  },
  {
    "WOOD": "0.00020491",
    "SKIN": "0.13500000",
    "STONE": "0.00023333",
    "FOOD": "0.00022541",
    "date_create": "2024-09-13 10:32:33"
  },
  {
    "STONE": "0.00023333",
    "SKIN": "0.13500000",
    "WOOD": "0.00020491",
    "FOOD": "0.00022541",
    "date_create": "2024-09-13 10:42:17"
  },
  {
    "FOOD": "0.00022541",
    "STONE": "0.00023333",
    "SKIN": "0.13500000",
    "WOOD": "0.00020491",
    "date_create": "2024-09-13 10:48:17"
  },
  {
    "SKIN": "0.13500000",
    "FOOD": "0.00022541",
    "STONE": "0.00023333",
    "WOOD": "0.00020491",
    "date_create": "2024-09-13 10:54:12"
  },
  {
    "FOOD": "0.00022541",
    "WOOD": "0.00020491",
    "STONE": "0.00023333",
    "SKIN": "0.13500000",
    "date_create": "2024-09-13 11:00:18"
  },
  {
    "SKIN": "0.13500000",
    "WOOD": "0.00020491",
    "STONE": "0.00023333",
    "FOOD": "0.00022541",
    "date_create": "2024-09-13 11:14:58"
  },
  {
    "SKIN": "0.13500000",
    "WOOD": "0.00020491",
    "STONE": "0.00023333",
    "FOOD": "0.00022541",
    "date_create": "2024-09-13 11:24:12"
  },
  {
    "STONE": "0.00023333",
    "SKIN": "0.13500000",
    "WOOD": "0.00020491",
    "FOOD": "0.00022541",
    "date_create": "2024-09-13 11:29:48"
  },
  {
    "FOOD": "0.00022541",
    "SKIN": "0.13500000",
    "WOOD": "0.00020491",
    "STONE": "0.00023333",
    "date_create": "2024-09-13 11:37:02"
  },
  {
    "WOOD": "0.00020491",
    "FOOD": "0.00022541",
    "SKIN": "0.13500000",
    "STONE": "0.00023333",
    "date_create": "2024-09-13 11:43:02"
  },
  {
    "SKIN": "0.13500000",
    "FOOD": "0.00022541",
    "WOOD": "0.00020491",
    "STONE": "0.00023333",
    "date_create": "2024-09-13 11:49:06"
  },
  {
    "STONE": "0.00023333",
    "SKIN": "0.13500000",
    "FOOD": "0.00022541",
    "WOOD": "0.00020491",
    "date_create": "2024-09-13 11:55:02"
  },
  {
    "STONE": "0.00023333",
    "WOOD": "0.00020491",
    "FOOD": "0.00022541",
    "SKIN": "0.13500000",
    "date_create": "2024-09-13 12:13:07"
  },
  {
    "WOOD": "0.00020491",
    "STONE": "0.00023333",
    "FOOD": "0.00022541",
    "SKIN": "0.13500000",
    "date_create": "2024-09-13 12:47:53"
  },
  {
    "STONE": "0.00023333",
    "SKIN": "0.13500000",
    "FOOD": "0.00022541",
    "WOOD": "0.00020491",
    "date_create": "2024-09-13 13:05:42"
  },
  {
    "STONE": "0.00023333",
    "SKIN": "0.13500000",
    "WOOD": "0.00020491",
    "FOOD": "0.00022541",
    "date_create": "2024-09-13 13:27:18"
  },
  {
    "STONE": "0.00023333",
    "FOOD": "0.00022541",
    "SKIN": "0.13500000",
    "WOOD": "0.00020491",
    "date_create": "2024-09-13 13:36:07"
  },
  {
    "SKIN": "0.13500000",
    "WOOD": "0.00020491",
    "FOOD": "0.00022541",
    "STONE": "0.00023333",
    "date_create": "2024-09-13 13:41:48"
  },
  {
    "FOOD": "0.00022541",
    "SKIN": "0.13500000",
    "STONE": "0.00023333",
    "WOOD": "0.00026585",
    "date_create": "2024-09-13 13:47:42"
  },
  {
    "STONE": "0.00024950",
    "SKIN": "0.13500000",
    "WOOD": "0.00026583",
    "FOOD": "0.00022541",
    "date_create": "2024-09-13 13:53:48"
  },
  {
    "STONE": "0.00024950",
    "SKIN": "0.13500000",
    "FOOD": "0.00022541",
    "WOOD": "0.00026550",
    "date_create": "2024-09-13 13:59:47"
  },
  {
    "STONE": "0.00024950",
    "FOOD": "0.00022541",
    "WOOD": "0.00026550",
    "SKIN": "0.13500000",
    "date_create": "2024-09-13 14:14:53"
  },
  {
    "STONE": "0.00024950",
    "WOOD": "0.00026550",
    "SKIN": "0.13500000",
    "FOOD": "0.00022541",
    "date_create": "2024-09-13 14:29:57"
  },
  {
    "FOOD": "0.00022541",
    "WOOD": "0.00026550",
    "SKIN": "0.13500000",
    "STONE": "0.00024950",
    "date_create": "2024-09-13 14:38:37"
  },
  {
    "FOOD": "0.00022541",
    "SKIN": "0.13500000",
    "STONE": "0.00024950",
    "WOOD": "0.00026550",
    "date_create": "2024-09-13 14:44:27"
  },
  {
    "SKIN": "0.13500000",
    "STONE": "0.00024950",
    "FOOD": "0.00022541",
    "WOOD": "0.00026550",
    "date_create": "2024-09-13 14:50:17"
  },
  {
    "STONE": "0.00024950",
    "WOOD": "0.00026550",
    "FOOD": "0.00022541",
    "SKIN": "0.13500000",
    "date_create": "2024-09-13 14:56:07"
  },
  {
    "STONE": "0.00024950",
    "SKIN": "0.13500000",
    "WOOD": "0.00026550",
    "FOOD": "0.00022541",
    "date_create": "2024-09-13 15:09:03"
  },
  {
    "WOOD": "0.00026550",
    "STONE": "0.00024950",
    "SKIN": "0.13500000",
    "FOOD": "0.00022541",
    "date_create": "2024-09-13 15:26:37"
  },
  {
    "FOOD": "0.00022541",
    "SKIN": "0.13500000",
    "STONE": "0.00024950",
    "WOOD": "0.00026550",
    "date_create": "2024-09-13 15:37:17"
  },
  {
    "FOOD": "0.00022541",
    "STONE": "0.00024950",
    "SKIN": "0.13500000",
    "WOOD": "0.00026550",
    "date_create": "2024-09-13 15:43:37"
  },
  {
    "SKIN": "0.13500000",
    "FOOD": "0.00022541",
    "STONE": "0.00024950",
    "WOOD": "0.00026550",
    "date_create": "2024-09-13 15:49:32"
  },
  {
    "WOOD": "0.00026550",
    "STONE": "0.00024950",
    "FOOD": "0.00022541",
    "SKIN": "0.13500000",
    "date_create": "2024-09-13 15:55:18"
  },
  {
    "WOOD": "0.00026550",
    "SKIN": "0.13500000",
    "STONE": "0.00024950",
    "FOOD": "0.00022541",
    "date_create": "2024-09-13 16:08:53"
  },
  {
    "STONE": "0.00024950",
    "WOOD": "0.00026550",
    "FOOD": "0.00022541",
    "SKIN": "0.13500000",
    "date_create": "2024-09-13 16:30:07"
  },
  {
    "WOOD": "0.00026550",
    "STONE": "0.00024950",
    "SKIN": "0.13500000",
    "FOOD": "0.00022541",
    "date_create": "2024-09-13 16:41:42"
  },
  {
    "STONE": "0.00024950",
    "WOOD": "0.00026550",
    "SKIN": "0.13500000",
    "FOOD": "0.00022541",
    "date_create": "2024-09-13 16:47:38"
  },
  {
    "WOOD": "0.00026550",
    "FOOD": "0.00022541",
    "STONE": "0.00024950",
    "SKIN": "0.13500000",
    "date_create": "2024-09-13 16:53:33"
  },
  {
    "STONE": "0.00024950",
    "SKIN": "0.13500000",
    "WOOD": "0.00026550",
    "FOOD": "0.00022541",
    "date_create": "2024-09-13 16:59:17"
  },
  {
    "SKIN": "0.13500000",
    "FOOD": "0.00022541",
    "STONE": "0.00024950",
    "WOOD": "0.00026550",
    "date_create": "2024-09-13 17:13:52"
  },
  {
    "SKIN": "0.13500000",
    "WOOD": "0.00026550",
    "FOOD": "0.00022541",
    "STONE": "0.00024950",
    "date_create": "2024-09-13 17:28:07"
  },
  {
    "SKIN": "0.13500000",
    "STONE": "0.00024950",
    "WOOD": "0.00026550",
    "FOOD": "0.00022541",
    "date_create": "2024-09-13 17:36:17"
  },
  {
    "SKIN": "0.13500000",
    "FOOD": "0.00022541",
    "WOOD": "0.00026550",
    "STONE": "0.00024950",
    "date_create": "2024-09-13 17:42:13"
  },
  {
    "SKIN": "0.13500000",
    "STONE": "0.00024950",
    "FOOD": "0.00022541",
    "date_create": "2024-09-13 17:48:02"
  },
  {
    "FOOD": "0.00022541",
    "SKIN": "0.13500000",
    "WOOD": "0.00026550",
    "STONE": "0.00024950",
    "date_create": "2024-09-13 17:54:02"
  },
  {
    "FOOD": "0.00022541",
    "SKIN": "0.13500000",
    "WOOD": "0.00026550",
    "date_create": "2024-09-13 18:00:03"
  },
  {
    "STONE": "0.00024950",
    "WOOD": "0.00026550",
    "FOOD": "0.00022541",
    "SKIN": "0.13500000",
    "date_create": "2024-09-13 18:23:07"
  },
  {
    "WOOD": "0.00026550",
    "SKIN": "0.13500000",
    "FOOD": "0.00022541",
    "STONE": "0.00024950",
    "date_create": "2024-09-13 18:38:38"
  },
  {
    "FOOD": "0.00022541",
    "SKIN": "0.13500000",
    "STONE": "0.00024950",
    "WOOD": "0.00026550",
    "date_create": "2024-09-13 18:46:28"
  },
  {
    "FOOD": "0.00022541",
    "STONE": "0.00024950",
    "WOOD": "0.00026550",
    "SKIN": "0.13500000",
    "date_create": "2024-09-13 18:52:17"
  },
  {
    "SKIN": "0.13500000",
    "STONE": "0.00024950",
    "FOOD": "0.00022541",
    "WOOD": "0.00026550",
    "date_create": "2024-09-13 18:58:03"
  },
  {
    "WOOD": "0.00026550",
    "STONE": "0.00024950",
    "FOOD": "0.00022541",
    "SKIN": "0.13500000",
    "date_create": "2024-09-13 19:10:38"
  },
  {
    "FOOD": "0.00022541",
    "WOOD": "0.00026550",
    "SKIN": "0.13500000",
    "STONE": "0.00024950",
    "date_create": "2024-09-13 19:21:32"
  },
  {
    "WOOD": "0.00026550",
    "FOOD": "0.00022541",
    "STONE": "0.00024750",
    "SKIN": "0.13500000",
    "date_create": "2024-09-13 19:27:32"
  },
  {
    "FOOD": "0.00022541",
    "STONE": "0.00024750",
    "SKIN": "0.13500000",
    "WOOD": "0.00026550",
    "date_create": "2024-09-13 19:34:47"
  },
  {
    "FOOD": "0.00022541",
    "WOOD": "0.00026550",
    "STONE": "0.00024750",
    "SKIN": "0.13500000",
    "date_create": "2024-09-13 19:40:37"
  },
  {
    "SKIN": "0.13500000",
    "STONE": "0.00024750",
    "FOOD": "0.00022541",
    "WOOD": "0.00026550",
    "date_create": "2024-09-13 19:46:42"
  },
  {
    "WOOD": "0.00026550",
    "STONE": "0.00024750",
    "SKIN": "0.13500000",
    "FOOD": "0.00022541",
    "date_create": "2024-09-13 19:52:33"
  },
  {
    "STONE": "0.00024750",
    "FOOD": "0.00022541",
    "WOOD": "0.00026550",
    "SKIN": "0.13500000",
    "date_create": "2024-09-13 19:58:27"
  },
  {
    "WOOD": "0.00026550",
    "FOOD": "0.00022541",
    "SKIN": "0.13500000",
    "STONE": "0.00024750",
    "date_create": "2024-09-13 20:14:33"
  },
  {
    "SKIN": "0.13500000",
    "STONE": "0.00024750",
    "FOOD": "0.00022541",
    "WOOD": "0.00026550",
    "date_create": "2024-09-13 20:27:38"
  },
  {
    "SKIN": "0.13500000",
    "WOOD": "0.00026550",
    "STONE": "0.00024750",
    "FOOD": "0.00022541",
    "date_create": "2024-09-13 20:35:48"
  },
  {
    "SKIN": "0.13500000",
    "WOOD": "0.00026550",
    "FOOD": "0.00022541",
    "STONE": "0.00024750",
    "date_create": "2024-09-13 20:41:52"
  },
  {
    "STONE": "0.00024750",
    "WOOD": "0.00026550",
    "SKIN": "0.13500000",
    "FOOD": "0.00022541",
    "date_create": "2024-09-13 20:47:53"
  },
  {
    "FOOD": "0.00022541",
    "WOOD": "0.00026550",
    "STONE": "0.00024750",
    "SKIN": "0.13500000",
    "date_create": "2024-09-13 20:53:42"
  },
  {
    "FOOD": "0.00022541",
    "STONE": "0.00024750",
    "WOOD": "0.00026550",
    "SKIN": "0.13500000",
    "date_create": "2024-09-13 20:59:22"
  },
  {
    "SKIN": "0.13500000",
    "WOOD": "0.00026550",
    "STONE": "0.00024750",
    "FOOD": "0.00022541",
    "date_create": "2024-09-13 21:14:53"
  },
  {
    "STONE": "0.00024750",
    "SKIN": "0.13500000",
    "FOOD": "0.00022541",
    "WOOD": "0.00026550",
    "date_create": "2024-09-13 21:26:06"
  },
  {
    "SKIN": "0.13500000",
    "WOOD": "0.00026550",
    "STONE": "0.00024750",
    "FOOD": "0.00022541",
    "date_create": "2024-09-13 21:32:32"
  },
  {
    "FOOD": "0.00022541",
    "WOOD": "0.00026550",
    "SKIN": "0.13500000",
    "STONE": "0.00024750",
    "date_create": "2024-09-13 21:38:53"
  },
  {
    "WOOD": "0.00026550",
    "SKIN": "0.13500000",
    "STONE": "0.00024750",
    "FOOD": "0.00022541",
    "date_create": "2024-09-13 21:44:48"
  },
  {
    "FOOD": "0.00022541",
    "SKIN": "0.13500000",
    "STONE": "0.00024750",
    "WOOD": "0.00026550",
    "date_create": "2024-09-13 21:50:37"
  },
  {
    "STONE": "0.00024750",
    "SKIN": "0.13500000",
    "WOOD": "0.00026550",
    "FOOD": "0.00022541",
    "date_create": "2024-09-13 21:56:37"
  },
  {
    "STONE": "0.00024750",
    "FOOD": "0.00022541",
    "WOOD": "0.00026550",
    "SKIN": "0.13500000",
    "date_create": "2024-09-13 22:10:06"
  },
  {
    "SKIN": "0.13500000",
    "STONE": "0.00024750",
    "WOOD": "0.00026550",
    "FOOD": "0.00022541",
    "date_create": "2024-09-13 22:28:27"
  },
  {
    "SKIN": "0.13500000",
    "STONE": "0.00024750",
    "FOOD": "0.00022541",
    "WOOD": "0.00026550",
    "date_create": "2024-09-13 22:37:47"
  },
  {
    "STONE": "0.00024750",
    "SKIN": "0.13500000",
    "FOOD": "0.00022541",
    "WOOD": "0.00026550",
    "date_create": "2024-09-13 22:43:43"
  },
  {
    "SKIN": "0.13500000",
    "WOOD": "0.00026550",
    "STONE": "0.00024750",
    "FOOD": "0.00022541",
    "date_create": "2024-09-13 22:49:38"
  }
]
